{
  "legislative_session": "38th",
  "identifier": "B 248-38",
  "title": "AN ACT TO\u00a0AMEND\u00a0CHAPTER 67 OF TITLE 10, GUAM CODE ANNOTATED, RELATIVE TO MODERNIZING AND EXPANDING THE GUAM OFFICE OF VETERANS AFFAIRS (GOVA) WITH THE INTENT OF STRENGTHENING SERVICES, IMPROVING ACCOUNTABILITY, ESTABLISHING RESPONSIBILTIES IN STATUTE, ENHANCING SUPPORT FOR GUAM\u2019S VETERANS, THEIR FAMILIES, AND TRANSITIONING SERVICE MEMBERS, AND TRANSFORMING THE OFFICE INTO A COMPREHENSIVE VETERANS AGENCY.",
  "from_organization": "~{\"classification\": \"legislature\"}",
  "classification": [
    "bill"
  ],
  "subject": [],
  "abstracts": [],
  "other_titles": [],
  "other_identifiers": [
    {
      "identifier": "ocd-bill-gu-38th-b24838"
    }
  ],
  "actions": [],
  "sponsorships": [
    {
      "name": "V. Anthony Ada",
      "classification": "primary",
      "entity_type": "person",
      "primary": true,
      "person_id": "~{\"chamber\": \"legislature\", \"name\": \"V. Anthony Ada\"}",
      "organization_id": null
    },
    {
      "name": "Christopher M. Due\u00f1as",
      "classification": "cosponsor",
      "entity_type": "person",
      "primary": false,
      "person_id": "~{\"chamber\": \"legislature\", \"name\": \"Christopher M. Due\\u00f1as\"}",
      "organization_id": null
    },
    {
      "name": "Vincent A. V. Borja",
      "classification": "cosponsor",
      "entity_type": "person",
      "primary": false,
      "person_id": "~{\"chamber\": \"legislature\", \"name\": \"Vincent A. V. Borja\"}",
      "organization_id": null
    }
  ],
  "related_bills": [],
  "versions": [
    {
      "note": "Bill No. 248-38 (COR)",
      "links": [
        {
          "url": "http://guamlegislature.gov/38th_Guam_Legislature/Bill_History_38th/STATUS Bill No. 248-38 (COR).pdf",
          "media_type": "application/pdf"
        }
      ],
      "date": "",
      "classification": ""
    }
  ],
  "documents": [],
  "citations": [],
  "sources": [
    {
      "url": "https://guamlegislature.gov/bills-page3/",
      "note": ""
    }
  ],
  "extras": {},
  "jurisdiction": {
    "id": "ocd-jurisdiction/country:us/territory:gu/government",
    "name": "Guam",
    "classification": "state",
    "division_id": "ocd-division/country:us/territory:gu"
  },
  "_processing": {
    "logs_latest_update": "2026-07-13T06:02:40Z"
  }
}